{
  "schemaVersion": 1,
  "id": "patchwork-event-dispatcher",
  "name": "Patchwork Event Dispatcher",
  "version": "${version}",
  "description": "Implements ForgeHooks, ForgeEventFactory, and more.",
  "environment": "*",
  "license": "LGPL-2.1-only",
  "icon": "assets/patchwork-event-dispatcher/icon.png",
  "contact": {
    "issues": "https://github.com/PatchworkMC/patchwork-api/issues",
    "sources": "https://github.com/PatchworkMC/patchwork-api"
  },
  "authors": [
    "PatchworkMC"
  ],
  "depends": {
    "fabricloader": ">=0.8.4",
    "patchwork-fml": "*",
    "patchwork-events-entity": "*",
    "patchwork-events-lifecycle": "*"
  },
  "custom": {
    "modmenu:api": true,
    "modmenu:parent": "patchwork"
  }
}
